pyrite/__init__.py
pyrite/_common.py
pyrite/atom_consts.py
pyrite/bounds.py
pyrite/view.py
pyrite/scoring/__init__.py
pyrite/scoring/_base.py
pyrite/scoring/bounds.py
pyrite/scoring/dependencies.py
pyrite/scoring/internal.py
pyrite/scoring/misc.py
pyrite/scoring/openmm.py
pyrite/scoring/protein.py
pyrite_chem-0.1.1.dist-info/METADATA
pyrite_chem-0.1.1.dist-info/WHEEL
pyrite_chem-0.1.1.dist-info/licenses/LICENSE
pyrite_chem-0.1.1.dist-info/RECORD
