Metadata-Version: 2.4
Name: pyrite_chem
Version: 0.1.1
Summary: Pyrite: utilities for molecular docking
Project-URL: Homepage, https://github.com/tcobanoglu/Pyrite
Author: Daan_Geerke_Lab
License: Copyright (c) 2025 Mart Johanan van der Lugt, David Alonzo Poole III
License-File: LICENSE
Classifier: License :: OSI Approved :: MIT License
Classifier: Operating System :: OS Independent
Classifier: Programming Language :: Python :: 3
Requires-Python: >=3.9
Requires-Dist: ipython>=8.0
Requires-Dist: ipywidgets>=8.0
Requires-Dist: numpy>=1.25
Requires-Dist: pillow>=9.0
Requires-Dist: py3dmol>=2.0
Requires-Dist: rdkit>=2023.9
Requires-Dist: scipy>=1.10
Provides-Extra: notebook
Requires-Dist: ipython>=7.0; extra == 'notebook'
Requires-Dist: ipywidgets<8.0,>=7.0; extra == 'notebook'
